progzee/__init__.py
progzee/cli.py
progzee/progzee.py
progzee-0.1.4.dist-info/LICENSE
progzee-0.1.4.dist-info/METADATA
progzee-0.1.4.dist-info/WHEEL
progzee-0.1.4.dist-info/entry_points.txt
progzee-0.1.4.dist-info/top_level.txt
progzee-0.1.4.dist-info/RECORD
